django_listing/__init__.py
django_listing/actions_buttons_column.py
django_listing/aggregations.py
django_listing/apps.py
django_listing/attached_form.py
django_listing/charts.py
django_listing/columns.py
django_listing/context.py
django_listing/exceptions.py
django_listing/filters.py
django_listing/form_fields.py
django_listing/html_attributes.py
django_listing/listing.py
django_listing/paginators.py
django_listing/record.py
django_listing/theme_config.py
django_listing/toolbar.py
django_listing/utils.py
django_listing/views.py
django_listing/locale/en/LC_MESSAGES/django.mo
django_listing/locale/en/LC_MESSAGES/django.po
django_listing/locale/fr/LC_MESSAGES/django.mo
django_listing/locale/fr/LC_MESSAGES/django.po
django_listing/static/django_listing/bootstrap4/css/animation.css
django_listing/static/django_listing/bootstrap4/css/django_listing-codes.css
django_listing/static/django_listing/bootstrap4/css/django_listing-embedded.css
django_listing/static/django_listing/bootstrap4/css/django_listing-ie7-codes.css
django_listing/static/django_listing/bootstrap4/css/django_listing-ie7.css
django_listing/static/django_listing/bootstrap4/css/django_listing.css
django_listing/static/django_listing/bootstrap4/css/django_listing.min.css
django_listing/static/django_listing/bootstrap4/font/django_listing.eot
django_listing/static/django_listing/bootstrap4/font/django_listing.svg
django_listing/static/django_listing/bootstrap4/font/django_listing.ttf
django_listing/static/django_listing/bootstrap4/font/django_listing.woff
django_listing/static/django_listing/bootstrap4/font/django_listing.woff2
django_listing/static/django_listing/bootstrap4/icons/csv.svg
django_listing/static/django_listing/bootstrap4/icons/dbf.svg
django_listing/static/django_listing/bootstrap4/icons/html.svg
django_listing/static/django_listing/bootstrap4/icons/json.svg
django_listing/static/django_listing/bootstrap4/icons/ods.svg
django_listing/static/django_listing/bootstrap4/icons/pdf.svg
django_listing-0.10.61.dist-info/LICENSE.rst
django_listing-0.10.61.dist-info/METADATA
django_listing-0.10.61.dist-info/WHEEL
django_listing-0.10.61.dist-info/top_level.txt
django_listing-0.10.61.dist-info/RECORD
