Metadata-Version: 2.1
Name: django-listing
Version: 0.10.61
Summary: Library for creating HTML listing / table / data grid
Home-page: https://github.com/elapouya/django-listing
Author: Eric Lapouyade
Author-email: elapouya@gmail.com
License: GPLv3+
Keywords: table,datatable,listing,data grid
Classifier: Intended Audience :: Developers
Classifier: Development Status :: 4 - Beta
Classifier: Framework :: Django
Classifier: Framework :: Django :: 2.0
Classifier: Framework :: Django :: 3.0
Classifier: Framework :: Django :: 4.0
Classifier: License :: OSI Approved :: GNU General Public License v3 or later (GPLv3+)
Classifier: Programming Language :: Python
Classifier: Programming Language :: Python :: 3
Classifier: Programming Language :: Python :: 3.7
Classifier: Programming Language :: Python :: 3.8
Classifier: Programming Language :: Python :: 3.9
Classifier: Programming Language :: Python :: 3.10
Classifier: Programming Language :: Python :: 3.11
Classifier: Programming Language :: Python :: 3.12
Classifier: Programming Language :: Python :: 3.13
License-File: LICENSE.rst
Requires-Dist: django>=2
Requires-Dist: tablib
Requires-Dist: django-autocomplete-light
Provides-Extra: docs
Requires-Dist: Sphinx; extra == "docs"
Requires-Dist: sphinxcontrib-napoleon; extra == "docs"
